pyfabm-0.1.data/purelib/pyfabm/__init__.py
pyfabm-0.1.data/purelib/pyfabm/complete_yaml.py
pyfabm-0.1.data/purelib/pyfabm/gui_qt.py
pyfabm-0.1.data/purelib/pyfabm/python_fabm.dll
pyfabm-0.1.data/purelib/pyfabm/utils/__init__.py
pyfabm-0.1.data/purelib/pyfabm/utils/fabm_complete_yaml.py
pyfabm-0.1.data/purelib/pyfabm/utils/fabm_configuration_gui.py
pyfabm-0.1.data/purelib/pyfabm/utils/fabm_describe_model.py
pyfabm-0.1.data/purelib/pyfabm/utils/fabm_evaluate.py
pyfabm-0.1.data/purelib/pyfabm/utils/fabm_stress_test.py
pyfabm-0.1.dist-info/METADATA
pyfabm-0.1.dist-info/RECORD
pyfabm-0.1.dist-info/WHEEL
pyfabm-0.1.dist-info/entry_points.txt
pyfabm-0.1.dist-info/top_level.txt
