Metadata-Version: 2.1
Name: pyfabm
Version: 0.1
Summary: Python driver for FABM
Home-page: https://github.com/fabm-model/fabm/tree/master/src/drivers/python
Author: Jorn Bruggeman
Author-email: jorn@bolding-bruggeman.com
License: GPL
Platform: UNKNOWN
